{"cameraMode":{"drawMode":0,"name":"Shaded","section":"Shading Mode"},"sceneLighting":false,"audioPlay":false,"sceneViewState":{"m_AlwaysRefresh":false,"showFog":true,"showSkybox":false,"showFlares":true,"showImageEffects":true,"showParticleSystems":true,"showVisualEffectGraphs":true,"m_FxEnabled":true},"in2DMode":false,"pivot":{"x":-9.247217178344727,"y":2.4847652912139894,"z":-0.037645258009433749},"rotation":{"x":0.08013702183961868,"y":0.7043735384941101,"z":-0.07989674806594849,"w":0.7006745338439941},"size":0.8660253882408142,"orthographic":false}